LICENSE
MANIFEST.in
README.md
package.json
setup.py
thinks_dash_components/Alert.py
thinks_dash_components/DesignableRadioItems.py
thinks_dash_components/IndexedDB.py
thinks_dash_components/InputNumber.py
thinks_dash_components/IosScrollWrapper.py
thinks_dash_components/LoadingWrapper.py
thinks_dash_components/MobileDropdown.py
thinks_dash_components/Notice.py
thinks_dash_components/OperationObserver.py
thinks_dash_components/Rotate.py
thinks_dash_components/SelectableBox.py
thinks_dash_components/StorageObserver.py
thinks_dash_components/TouchableComponent.py
thinks_dash_components/UrlObserver.py
thinks_dash_components/_ComponentTemplate.py
thinks_dash_components/__init__.py
thinks_dash_components/_imports_.py
thinks_dash_components/metadata.json
thinks_dash_components/package-info.json
thinks_dash_components/thinks_dash_components.min.js
thinks_dash_components/thinks_dash_components.min.js.map
thinks_dash_components.egg-info/PKG-INFO
thinks_dash_components.egg-info/SOURCES.txt
thinks_dash_components.egg-info/dependency_links.txt
thinks_dash_components.egg-info/top_level.txt