Metadata-Version: 2.1
Name: thinks-dash-components
Version: 0.3.4
Summary: Dash Extension Components for Smartphones
Author: thinkup-sol <s_matsumoto@thinkup-sol.co.jp>
License: MIT
Classifier: Framework :: Dash
License-File: LICENSE
